tools/__init__.py
tools/sc/__init__.py
tools/sc/_sc.py
tools/tools/__init__.py
tools/tools/_tools.py
kttools-0.2.2.dist-info/LICENSE
kttools-0.2.2.dist-info/METADATA
kttools-0.2.2.dist-info/WHEEL
kttools-0.2.2.dist-info/RECORD
