Metadata-Version: 2.1
Name: kttools
Version: 0.2.2
Summary: Kelvin's miscellaneous tools for python
License: MIT
Author: Zewen Kelvin Tuong
Author-email: z.tuong@uq.edu.au
Requires-Python: >=3.8,<3.11
Classifier: Intended Audience :: Developers
Classifier: Intended Audience :: Science/Research
Classifier: License :: OSI Approved :: MIT License
Classifier: Programming Language :: Python :: 3
Classifier: Programming Language :: Python :: 3.8
Classifier: Programming Language :: Python :: 3.9
Classifier: Programming Language :: Python :: 3.10
Provides-Extra: docs
Requires-Dist: anndata (>=0.7.6,<0.9.2)
Requires-Dist: matplotlib (>=3.5.2,<3.7.2)
Requires-Dist: numpy (>=1.21.6,<1.24.4)
Requires-Dist: pandas (>=1.2.4,<2.0.2)
Requires-Dist: readthedocs-sphinx-ext ; extra == "docs"
Requires-Dist: recommonmark ; extra == "docs"
Requires-Dist: scanpy (>=1.7.1,<1.9.4)
Requires-Dist: sphinx-autodoc-typehints ; extra == "docs"
Requires-Dist: sphinx_rtd_theme ; extra == "docs"
